systemhealthai/.env.template
systemhealthai/__init__.py
systemhealthai/example_mcp_server_config.json
systemhealthai/main.py
systemhealthai/prompts.py
systemhealthai/shai.py
systemhealthai-0.1.0.dist-info/LICENSE
systemhealthai-0.1.0.dist-info/METADATA
systemhealthai-0.1.0.dist-info/WHEEL
systemhealthai-0.1.0.dist-info/entry_points.txt
systemhealthai-0.1.0.dist-info/RECORD
