Metadata-Version: 2.3
Name: systemhealthai
Version: 0.1.0
Summary: An SRE AI agent to analyze, and report back on health of a node
Author: ajinkyakadam
Author-email: ajenkya.kadam@gmail.com
Requires-Python: >=3.11,<4.0
Classifier: Programming Language :: Python :: 3
Classifier: Programming Language :: Python :: 3.11
Classifier: Programming Language :: Python :: 3.12
Classifier: Programming Language :: Python :: 3.13
Requires-Dist: aiohttp (>=3.11.18,<4.0.0)
Requires-Dist: asyncio (>=3.4.3,<4.0.0)
Requires-Dist: fastembed (>=0.6.1,<0.7.0)
Requires-Dist: jinja2 (>=3.1.6,<4.0.0)
Requires-Dist: langchain (>=0.3.24,<0.4.0)
Requires-Dist: langchain-openai (>=0.3.14,<0.4.0)
Requires-Dist: mcp-use (>=1.2.12,<2.0.0)
Requires-Dist: python-dotenv (>=1.1.0,<2.0.0)
Requires-Dist: trio (>=0.30.0,<0.31.0)
Requires-Dist: typer (>=0.15.3,<0.16.0)
